Metadata-Version: 1.0
Name: distributions-package-iml
Version: 0.1
Summary: Gaussian distributions
Home-page: UNKNOWN
Author: Isaac Looremeta
Author-email: isakm3@gmail.com
License: UNKNOWN
Platform: UNKNOWN
